JavascriptBianchengJingjieZhongwenDisanban/README.md
JavascriptBianchengJingjieZhongwenDisanban/__init__.py
JavascriptBianchengJingjieZhongwenDisanban/__main__.py
JavascriptBianchengJingjieZhongwenDisanban/file.epub
JavascriptBianchengJingjieZhongwenDisanban/index.html
JavascriptBianchengJingjieZhongwenDisanban/css/__init__.py
JavascriptBianchengJingjieZhongwenDisanban/css/annotations.css
JavascriptBianchengJingjieZhongwenDisanban/css/main.css
JavascriptBianchengJingjieZhongwenDisanban/css/normalize.css
JavascriptBianchengJingjieZhongwenDisanban/css/popup.css
JavascriptBianchengJingjieZhongwenDisanban/font/__init__.py
JavascriptBianchengJingjieZhongwenDisanban/font/fontello.eot
JavascriptBianchengJingjieZhongwenDisanban/font/fontello.svg
JavascriptBianchengJingjieZhongwenDisanban/font/fontello.ttf
JavascriptBianchengJingjieZhongwenDisanban/font/fontello.woff
JavascriptBianchengJingjieZhongwenDisanban/img/__init__.py
JavascriptBianchengJingjieZhongwenDisanban/img/annotator-glyph-sprite.png
JavascriptBianchengJingjieZhongwenDisanban/img/annotator-icon-sprite.png
JavascriptBianchengJingjieZhongwenDisanban/img/apple-touch-icon.png
JavascriptBianchengJingjieZhongwenDisanban/img/cancelfullscreen.png
JavascriptBianchengJingjieZhongwenDisanban/img/close.png
JavascriptBianchengJingjieZhongwenDisanban/img/fullscreen.png
JavascriptBianchengJingjieZhongwenDisanban/img/loader.gif
JavascriptBianchengJingjieZhongwenDisanban/img/menu-icon.png
JavascriptBianchengJingjieZhongwenDisanban/img/save.png
JavascriptBianchengJingjieZhongwenDisanban/img/saved.png
JavascriptBianchengJingjieZhongwenDisanban/img/settings-s.png
JavascriptBianchengJingjieZhongwenDisanban/img/settings.png
JavascriptBianchengJingjieZhongwenDisanban/img/star.png
JavascriptBianchengJingjieZhongwenDisanban/js/__init__.py
JavascriptBianchengJingjieZhongwenDisanban/js/epub.js
JavascriptBianchengJingjieZhongwenDisanban/js/epub.min.js
JavascriptBianchengJingjieZhongwenDisanban/js/epub.min.map
javascript_biancheng_jingjie_zhongwen_disanban-2024.3.3.0.dist-info/METADATA
javascript_biancheng_jingjie_zhongwen_disanban-2024.3.3.0.dist-info/WHEEL
javascript_biancheng_jingjie_zhongwen_disanban-2024.3.3.0.dist-info/entry_points.txt
javascript_biancheng_jingjie_zhongwen_disanban-2024.3.3.0.dist-info/top_level.txt
javascript_biancheng_jingjie_zhongwen_disanban-2024.3.3.0.dist-info/RECORD
